README.md
setup.py
config/keyboard/Readme.md
config/keyboard/desktop.conf
config/keyboard/laptop.conf
config/keyboard/nvda-desktop.conf
config/keyboard/nvda-laptop.conf
config/keyboard/pty.conf
config/keyboard/pty2.conf
config/punctuation/de.conf
config/punctuation/default.conf
config/punctuation/en.conf
config/punctuation/es.conf
config/punctuation/fr.conf
config/punctuation/pl.conf
config/scripts/wlan__-__key_y.sh
config/settings/espeak.settings.conf
config/settings/settings-daemon.conf
config/settings/settings-pty.conf
config/settings/settings.conf
config/settings/settings.conf.example
config/settings/settings.conf.storm
config/settings/speech-dispatcher.settings.conf
config/sound//template/soundicons.conf
config/sound/default/Accept.wav
config/sound/default/Announce.wav
config/sound/default/BrailleOff.wav
config/sound/default/BrailleOn.wav
config/sound/default/Cancel.wav
config/sound/default/Caps.wav
config/sound/default/ChangeTTY.wav
config/sound/default/ContentChanged.wav
config/sound/default/CopyToClipboard.wav
config/sound/default/EmptyLine.wav
config/sound/default/EndOfLine.wav
config/sound/default/EndOfScreen.wav
config/sound/default/ErrorBraille.wav
config/sound/default/ErrorScreen.wav
config/sound/default/ErrorSpeech.wav
config/sound/default/PTYBypass.wav
config/sound/default/PasteClipboardOnScreen.wav
config/sound/default/PlaceEndMark.wav
config/sound/default/PlaceStartMark.wav
config/sound/default/PromotedText.wav
config/sound/default/ScreenReaderOff.wav
config/sound/default/ScreenReaderOn.wav
config/sound/default/SoundOff.wav
config/sound/default/SoundOn.wav
config/sound/default/SpeechOff.wav
config/sound/default/SpeechOn.wav
config/sound/default/StartOfLine.wav
config/sound/default/StartOfScreen.wav
config/sound/default/barrier.wav
config/sound/default/barrier_end.wav
config/sound/default/barrier_start.wav
config/sound/default/has_attribute.wav
config/sound/default/mispell.wav
config/sound/default/soundicons.conf
docu/fenrir.1
src/fenrir
src/fenrir_screenreader.egg-info/PKG-INFO
src/fenrir_screenreader.egg-info/SOURCES.txt
src/fenrir_screenreader.egg-info/dependency_links.txt
src/fenrir_screenreader.egg-info/not-zip-safe
src/fenrir_screenreader.egg-info/requires.txt
src/fenrir_screenreader.egg-info/top_level.txt
