Metadata-Version: 1.1
Name: fenrir-screenreader
Version: 1.9.6.post1
Summary: A TTY Screen Reader for Linux.
Home-page: https://github.com/chrys87/fenrir/
Author: Chrys, Storm_dragon, Jeremiah and others
Author-email: chrysg@linux-a11y.org
License: License :: OSI Approved :: GNU General Public License v3 or later (GPLv3+)
Download-URL: https://github.com/chrys87/fenrir/archive/1.9.6.tar.gz
Keywords: screenreader,a11y,accessibility,terminal,TTY,console
Platform: UNKNOWN
Classifier: Programming Language :: Python
Classifier: License :: OSI Approved :: GNU Lesser General Public License v3 (LGPLv3)
Classifier: Development Status :: 5 - Production/Stable
Classifier: Topic :: Multimedia :: Sound/Audio :: Speech
Classifier: Environment :: Console
